 {  
     "NomeDoCliente1": {
         "ip": "179.108.233.122",
         "poderes": ["universestore_power_transitionflower", "universestore_power_waterjump", "universestore_power_bombwater", "universestore_power_seat", "universestore_power_darkshadow","universestore_power_mirrorteleport"],
         "__comentario": "Angels"
     },
     "NomeDoCliente2": {
         "ip": "45.146.81.237",
         "poderes": ["universestore_power_seat", "nome_do_script2"],
        "__comentario": "Valenwood"
     },
  "NomeDoCliente3": {
         "ip": "181.215.254.203",
         "poderes": ["universestore_power_seat", "nome_do_script2"],
        "__comentario": "EnigmaFalls.Goiaba"
     }
 }
